{"document_id": "320001081806", "content": "Container: ONEU0053223 (C4) | Consignee: WILSON CANADA | Seal Number: SGAH04575 | Origin/Load: YANGON(MMRGN) | Discharge: VANCOUVER, BC(CAVAN) → Last CY location: TORONTO, ON(CATOR) | Final Destination: BELLEVILLE, ON(CABLV) | Destination service: DOOR(CY) | Current shipment status: EMPTY CONTAINER RETURNED\n\nKey dates: ETD LP: 07-Feb-25 | ETA DP: 03-May-25 | ATA DP (optimal): 04-May-25 | ETA FD (optimal): 26-May-25 Delay snapshot: DP delay: delay, Δ≈1 day(s) | FD delay: early, Δ≈-3 day(s)\n\nRoute summary: Origin/Load: YANGON(MMRGN) → Transshipment: SINGAPORE(SGSIN) → Discharge: VANCOUVER, BC(CAVAN) → Delivery at: BELLEVILLE, ON(CABLV) Last CY location: TORONTO, ON(CATOR) Vessel summary: First vessel: CAPE FELTON | Final vessel: YM TRANQUILITY Carrier summary: Operated by OCEAN NETWORK EXPRESS PTE. LTD\n\nMilestones: Overall shipment status: EMPTY CONTAINER RETURNED || Leg 1 (POR → Load Port) [COMPLETED]: YANGON(MMRGN) → YANGON(MMRGN); departed YANGON(MMRGN) on 2025-02-07. || Leg 2 (Load Port → TS) [COMPLETED]: YANGON(MMRGN) → SINGAPORE(SGSIN); arrived TS SINGAPORE(SGSIN) on 2025-02-12; departed TS on 2025-02-27 || Leg 3 (TS/Load → DP) [COMPLETED]: SINGAPORE(SGSIN) → VANCOUVER, BC(CAVAN); arrived VANCOUVER, BC(CAVAN) on 2025-05-04 (delayed by ~1 day(s) vs ETA DP.) || Leg 4 (DP → Last CY) [COMPLETED]: VANCOUVER, BC(CAVAN) → TORONTO, ON(CATOR); departed DP area (VANCOUVER, BC(CAVAN)) on 2025-05-09, arrived TORONTO, ON(CATOR) on 2025-05-16. Rail events: rail load VANCOUVER, BC(CAVAN) on 2025-05-09; rail depart WINNIPEG, MB(CAWNP) on 2025-05-14; rail arrive BRAMPTON, ON(CABRP) on 2025-05-17 || Leg 5 (Last CY → Final) [COMPLETED]: TORONTO, ON(CATOR) → BELLEVILLE, ON(CABLV); delivered at BELLEVILLE, ON(CABLV) on 2025-05-23; empty container returned at KLEINBURG, ON(CAKBG) on 2025-05-23 (early by ~3 day(s) vs ETA FD.) Critical dates: Leg 1 (POR → Load Port): YANGON(MMRGN) → YANGON(MMRGN) | ETD 07-Feb-25, ATD 07-Feb-25 || Leg 2 (Load → TS): YANGON(MMRGN) → SINGAPORE(SGSIN) | ATA 12-Feb-25, ATD 27-Feb-25 || Leg 3 (Ocean to DP): SINGAPORE(SGSIN) → VANCOUVER, BC(CAVAN) | ATA_DP 04-May-25 || Leg 4 (DP → Last CY): VANCOUVER, BC(CAVAN) → TORONTO, ON(CATOR) | OUT_GATE_DP 09-May-25, ARR_LAST_CY 16-May-25 || Leg 5 (Last CY → Final): TORONTO, ON(CATOR) → BELLEVILLE, ON(CABLV) | DELIVERY 23-May-25, EMPTY_RET 23-May-25 Delay analysis: Ocean / discharge-port leg is delayed versus ETA at DP by ~1 day(s).\n\nOperational status: Current departure status: False | Current arrival status: False\n\nOperational events: Cargo ready: 03-Feb-25, 03-Feb-25 | Cargo received: 04-Feb-25, 04-Feb-25 | Empty container dispatch: 01-Feb-25 @ YANGON(MMRGN) | In-gate: 04-Feb-25 @ YANGON(MMRGN) | Carrier vehicle load: 06-Feb-25 @ YANGON(MMRGN) | Carrier vehicle unload: 05-May-25 @ VANCOUVER, BC(CAVAN) | Vehicle departure: 07-Feb-25 @ YANGON(MMRGN) | Vehicle arrival: 04-May-25 @ VANCOUVER, BC(CAVAN) | Out-gate from DP: 09-May-25 @ VANCOUVER, BC(CAVAN) | Equipment arrived at last CY: 16-May-25 @ TORONTO, ON(CATOR) | Out-gate at last CY location: NAN | Rail load: 09-May-25 @ VANCOUVER, BC(CAVAN) | Rail departure: 14-May-25 @ WINNIPEG, MB(CAWNP) | Rail arrival: 17-May-25 @ BRAMPTON, ON(CABRP)\n\nCargo metrics: weight 2491.5 kg volume 54.45 m3 Cargo count: 550 CTN Detail cargo: 550 PCS CO2: tank-to-wheel 266.101 | well-to-wheel 291.877\n\nFree days: Demurrage free days: 4.0 | Detention free days: 4.0\n\nReferences: PO Numbers: 5302836696 | Booking Numbers: MM2003117 | FCR Numbers: MM2003117 | Ocean BL Numbers: ONEYYGNF00803400 | Job No: MM2ASC0053 | MCS HBL: NAN | Service Contract: ATL0055B24(MM2003117)\n\nParties & service: Consignee: WILSON CANADA | Ship-to party: NAN | Supplier/Vendor: PINNACLE SPORTING GOODS (MYANMAR)(0038566) | Manufacturer: PINNACLE SPORTING GOODS (MYANMAR)(0038566) | Job type: OCB | Transport mode: SEA | Hot container flag: False | Booking approval status: (MM2003117)", "metadata": {"job_no": "MM2ASC0053", "container_number": "ONEU0053223", "container_type": "C4", "destination_service": "DOOR(CY)", "po_numbers": "5302836696", "booking_numbers": "MM2003117", "fcr_numbers": "MM2003117", "obl_nos": "ONEYYGNF00803400", "load_port": "YANGON(MMRGN)", "final_load_port": "SINGAPORE(SGSIN)", "discharge_port": "VANCOUVER, BC(CAVAN)", "last_cy_location": "VANCOUVER, BC(CAVAN)", "place_of_receipt": "YANGON(MMRGN)", "place_of_delivery": "BELLEVILLE, ON(CABLV)", "final_destination": "BELLEVILLE, ON(CABLV)", "first_vessel_name": "CAPE FELTON", "final_carrier_name": "OCEAN NETWORK EXPRESS PTE. LTD", "final_vessel_name": "YM TRANQUILITY", "true_carrier_scac_name": "OCEAN NETWORK EXPRESS PTE. LTD", "etd_lp_date": "2025-02-07T00:00:00", "etd_flp_date": "2025-02-27T00:00:00", "eta_dp_date": "2025-05-03T00:00:00", "eta_fd_date": "2025-05-20T00:00:00", "revised_eta_date": "2025-05-03T00:00:00", "predictive_eta_date": "2025-05-05T00:00:00", "atd_lp_date": "2025-02-07T00:00:00", "ata_flp_date": "2025-02-12T00:00:00", "atd_flp_date": "2025-02-27T00:00:00", "ata_dp_date": "2025-05-04T00:00:00", "derived_ata_dp_date": "2025-05-04T00:00:00", "revised_eta_fd_date": "2025-05-26T00:00:00", "predictive_eta_fd_date": "2025-05-26T00:00:00", "cargo_receiveds_date": ["2025-02-04T00:00:00", "2025-02-04T00:00:00"], "detention_free_days": "4.0", "demurrage_free_days": "4.0", "hot_container_flag": false, "supplier_vendor_name": "PINNACLE SPORTING GOODS (MYANMAR)(0038566)", "manufacturer_name": "PINNACLE SPORTING GOODS (MYANMAR)(0038566)", "ship_to_party_name": "NAN", "booking_approval_status": "(MM2003117)", "service_contract_number": "ATL0055B24(MM2003117)", "carrier_vehicle_load_date": "2025-02-06T00:00:00", "carrier_vehicle_load_lcn": "YANGON(MMRGN)", "vehicle_departure_date": "2025-02-07T00:00:00", "vehicle_departure_lcn": "YANGON(MMRGN)", "vehicle_arrival_date": "2025-05-04T00:00:00", "vehicle_arrival_lcn": "VANCOUVER, BC(CAVAN)", "carrier_vehicle_unload_date": "2025-05-05T00:00:00", "carrier_vehicle_unload_lcn": "VANCOUVER, BC(CAVAN)", "out_gate_from_dp_date": "2025-05-09T00:00:00", "out_gate_from_dp_lcn": "VANCOUVER, BC(CAVAN)", "equipment_arrived_at_last_cy_date": "2025-05-16T00:00:00", "equipment_arrived_at_last_cy_lcn": "TORONTO, ON(CATOR)", "out_gate_at_last_cy_date": "NaT", "out_gate_at_last_cy_lcn": "NAN", "delivery_to_consignee_date": "2025-05-23T00:00:00", "delivery_to_consignee_lcn": "BELLEVILLE, ON(CABLV)", "empty_container_return_date": "2025-05-23T00:00:00", "empty_container_return_lcn": "KLEINBURG, ON(CAKBG)", "co2_tank_on_wheel": "266.101", "co2_well_to_wheel": "291.877", "job_type": "OCB", "mcs_hbl": "NAN", "transport_mode": "SEA", "rail_load_dp_date": "2025-05-09T00:00:00", "rail_load_dp_lcn": "VANCOUVER, BC(CAVAN)", "rail_departure_dp_date": "2025-05-14T00:00:00", "rail_departure_dp_lcn": "WINNIPEG, MB(CAWNP)", "rail_arrival_destination_date": "2025-05-17T00:00:00", "rail_arrival_destination_lcn": "BRAMPTON, ON(CABRP)", "cargo_ready_date": ["2025-02-03T00:00:00", "2025-02-03T00:00:00"], "in-dc_date": "NaT", "cargo_weight_kg": "2491.5", "cargo_measure_cubic_meter": "54.45", "cargo_count": "550", "cargo_um": "CTN", "cargo_detail_count": "550", "detail_cargo_um": "PCS", "856_filing_status": "", "get_isf_submission_date": null, "seal_number": "SGAH04575", "in_gate_date": "2025-02-04T00:00:00", "in_gate_lcn": "YANGON(MMRGN)", "empty_container_dispatch_date": "2025-02-01T00:00:00", "empty_container_dispatch_lcn": "YANGON(MMRGN)", "consignee_name": "WILSON CANADA", "consignee_codes": ["0001615"], "optimal_ata_dp_date": "2025-05-04T00:00:00", "optimal_eta_fd_date": "2025-05-26T00:00:00", "delayed_dp": "delay", "dp_delayed_dur": 1, "delayed_fd": "early", "fd_delayed_dur": -3, "shipment_status": "EMPTY_CONTAINER_RETURNED", "critical_dates_summary": "Leg 1 (POR → Load Port): YANGON(MMRGN) → YANGON(MMRGN) | ETD 07-Feb-25, ATD 07-Feb-25 || Leg 2 (Load → TS): YANGON(MMRGN) → SINGAPORE(SGSIN) | ATA 12-Feb-25, ATD 27-Feb-25 || Leg 3 (Ocean to DP): SINGAPORE(SGSIN) → VANCOUVER, BC(CAVAN) | ATA_DP 04-May-25 || Leg 4 (DP → Last CY): VANCOUVER, BC(CAVAN) → TORONTO, ON(CATOR) | OUT_GATE_DP 09-May-25, ARR_LAST_CY 16-May-25 || Leg 5 (Last CY → Final): TORONTO, ON(CATOR) → BELLEVILLE, ON(CABLV) | DELIVERY 23-May-25, EMPTY_RET 23-May-25", "delay_reason_summary": "Ocean / discharge-port leg is delayed versus ETA at DP by ~1 day(s).", "workflow_gap_flags": "none_detected", "milestones": "Overall shipment status: EMPTY CONTAINER RETURNED || Leg 1 (POR → Load Port) [COMPLETED]: YANGON(MMRGN) → YANGON(MMRGN); departed YANGON(MMRGN) on 2025-02-07. || Leg 2 (Load Port → TS) [COMPLETED]: YANGON(MMRGN) → SINGAPORE(SGSIN); arrived TS SINGAPORE(SGSIN) on 2025-02-12; departed TS on 2025-02-27 || Leg 3 (TS/Load → DP) [COMPLETED]: SINGAPORE(SGSIN) → VANCOUVER, BC(CAVAN); arrived VANCOUVER, BC(CAVAN) on 2025-05-04 (delayed by ~1 day(s) vs ETA DP.) || Leg 4 (DP → Last CY) [COMPLETED]: VANCOUVER, BC(CAVAN) → TORONTO, ON(CATOR); departed DP area (VANCOUVER, BC(CAVAN)) on 2025-05-09, arrived TORONTO, ON(CATOR) on 2025-05-16. Rail events: rail load VANCOUVER, BC(CAVAN) on 2025-05-09; rail depart WINNIPEG, MB(CAWNP) on 2025-05-14; rail arrive BRAMPTON, ON(CABRP) on 2025-05-17 || Leg 5 (Last CY → Final) [COMPLETED]: TORONTO, ON(CATOR) → BELLEVILLE, ON(CABLV); delivered at BELLEVILLE, ON(CABLV) on 2025-05-23; empty container returned at KLEINBURG, ON(CAKBG) on 2025-05-23 (early by ~3 day(s) vs ETA FD.)", "vessel_summary": "First vessel: CAPE FELTON | Final vessel: YM TRANQUILITY", "carrier_summary": "Operated by OCEAN NETWORK EXPRESS PTE. LTD", "port_route_summary": "Origin/Load: YANGON(MMRGN) → Transshipment: SINGAPORE(SGSIN) → Discharge: VANCOUVER, BC(CAVAN) → Delivery at: BELLEVILLE, ON(CABLV)", "source_group": "2025-02", "source_month_tag": "feb_25"}, "consignee_code": "['0001615']"}
{"document_id": "320001081807", "content": "Container: BMOU1501333 (S2) | Consignee: WILSON CANADA | Seal Number: SGAH04573 | Origin/Load: YANGON(MMRGN) | Discharge: VANCOUVER, BC(CAVAN) → Last CY location: TORONTO, ON(CATOR) | Final Destination: BELLEVILLE, ON(CABLV) | Destination service: DOOR(CY) | Current shipment status: EMPTY CONTAINER RETURNED\n\nKey dates: ETD LP: 07-Feb-25 | ETA DP: 03-May-25 | ATA DP (optimal): 04-May-25 | ETA FD (optimal): 23-May-25 Delay snapshot: DP delay: delay, Δ≈1 day(s) | FD delay: early, Δ≈-10 day(s)\n\nRoute summary: Origin/Load: YANGON(MMRGN) → Transshipment: SINGAPORE(SGSIN) → Discharge: VANCOUVER, BC(CAVAN) → Delivery at: BELLEVILLE, ON(CABLV) Last CY location: TORONTO, ON(CATOR) Vessel summary: First vessel: CAPE FELTON | Final vessel: YM TRANQUILITY Carrier summary: Operated by OCEAN NETWORK EXPRESS PTE. LTD\n\nMilestones: Overall shipment status: EMPTY CONTAINER RETURNED || Leg 1 (POR → Load Port) [COMPLETED]: YANGON(MMRGN) → YANGON(MMRGN); departed YANGON(MMRGN) on 2025-02-07. || Leg 2 (Load Port → TS) [COMPLETED]: YANGON(MMRGN) → SINGAPORE(SGSIN); arrived TS SINGAPORE(SGSIN) on 2025-02-12; departed TS on 2025-02-27 || Leg 3 (TS/Load → DP) [COMPLETED]: SINGAPORE(SGSIN) → VANCOUVER, BC(CAVAN); arrived VANCOUVER, BC(CAVAN) on 2025-05-04 (delayed by ~1 day(s) vs ETA DP.) || Leg 4 (DP → Last CY) [COMPLETED]: VANCOUVER, BC(CAVAN) → TORONTO, ON(CATOR); departed DP area (VANCOUVER, BC(CAVAN)) on 2025-05-06, arrived TORONTO, ON(CATOR) on 2025-05-12. Rail events: rail load VANCOUVER, BC(CAVAN) on 2025-05-05; rail depart WINNIPEG, MB(CAWNP) on 2025-05-10; rail arrive BRAMPTON, ON(CABRP) on 2025-05-13 || Leg 5 (Last CY → Final) [COMPLETED]: TORONTO, ON(CATOR) → BELLEVILLE, ON(CABLV); delivered at BELLEVILLE, ON(CABLV) on 2025-05-13; empty container returned at TORONTO, ON(CATOR) on 2025-05-14 (early by ~10 day(s) vs ETA FD.) Critical dates: Leg 1 (POR → Load Port): YANGON(MMRGN) → YANGON(MMRGN) | ETD 07-Feb-25, ATD 07-Feb-25 || Leg 2 (Load → TS): YANGON(MMRGN) → SINGAPORE(SGSIN) | ATA 12-Feb-25, ATD 27-Feb-25 || Leg 3 (Ocean to DP): SINGAPORE(SGSIN) → VANCOUVER, BC(CAVAN) | ATA_DP 04-May-25 || Leg 4 (DP → Last CY): VANCOUVER, BC(CAVAN) → TORONTO, ON(CATOR) | OUT_GATE_DP 06-May-25, ARR_LAST_CY 12-May-25 || Leg 5 (Last CY → Final): TORONTO, ON(CATOR) → BELLEVILLE, ON(CABLV) | DELIVERY 13-May-25, EMPTY_RET 14-May-25 Delay analysis: Ocean / discharge-port leg is delayed versus ETA at DP by ~1 day(s).\n\nOperational status: Current departure status: False | Current arrival status: False\n\nOperational events: Cargo ready: 03-Feb-25, 03-Feb-25 | Cargo received: 04-Feb-25, 04-Feb-25 | Empty container dispatch: 01-Feb-25 @ YANGON(MMRGN) | In-gate: 04-Feb-25 @ YANGON(MMRGN) | Carrier vehicle load: 06-Feb-25 @ YANGON(MMRGN) | Carrier vehicle unload: 05-May-25 @ VANCOUVER, BC(CAVAN) | Vehicle departure: 07-Feb-25 @ YANGON(MMRGN) | Vehicle arrival: 04-May-25 @ VANCOUVER, BC(CAVAN) | Out-gate from DP: 06-May-25 @ VANCOUVER, BC(CAVAN) | Equipment arrived at last CY: 12-May-25 @ TORONTO, ON(CATOR) | Out-gate at last CY location: NAN | Rail load: 05-May-25 @ VANCOUVER, BC(CAVAN) | Rail departure: 10-May-25 @ WINNIPEG, MB(CAWNP) | Rail arrival: 13-May-25 @ BRAMPTON, ON(CABRP)\n\nCargo metrics: weight 1266.5 kg volume 25.2 m3 Cargo count: 300 CTN Detail cargo: 300 PCS CO2: tank-to-wheel 135.267 | well-to-wheel 148.369\n\nFree days: Demurrage free days: 4.0 | Detention free days: 4.0\n\nReferences: PO Numbers: 5302836696 | Booking Numbers: MM2003117 | FCR Numbers: MM2003117 | Ocean BL Numbers: ONEYYGNF00803400 | Job No: MM2ASC0053 | MCS HBL: NAN | Service Contract: ATL0055B24(MM2003117)\n\nParties & service: Consignee: WILSON CANADA | Ship-to party: NAN | Supplier/Vendor: PINNACLE SPORTING GOODS (MYANMAR)(0038566) | Manufacturer: PINNACLE SPORTING GOODS (MYANMAR)(0038566) | Job type: OCB | Transport mode: SEA | Hot container flag: False | Booking approval status: (MM2003117)", "metadata": {"job_no": "MM2ASC0053", "container_number": "BMOU1501333", "container_type": "S2", "destination_service": "DOOR(CY)", "po_numbers": "5302836696", "booking_numbers": "MM2003117", "fcr_numbers": "MM2003117", "obl_nos": "ONEYYGNF00803400", "load_port": "YANGON(MMRGN)", "final_load_port": "SINGAPORE(SGSIN)", "discharge_port": "VANCOUVER, BC(CAVAN)", "last_cy_location": "VANCOUVER, BC(CAVAN)", "place_of_receipt": "YANGON(MMRGN)", "place_of_delivery": "BELLEVILLE, ON(CABLV)", "final_destination": "BELLEVILLE, ON(CABLV)", "first_vessel_name": "CAPE FELTON", "final_carrier_name": "OCEAN NETWORK EXPRESS PTE. LTD", "final_vessel_name": "YM TRANQUILITY", "true_carrier_scac_name": "OCEAN NETWORK EXPRESS PTE. LTD", "etd_lp_date": "2025-02-07T00:00:00", "etd_flp_date": "2025-02-27T00:00:00", "eta_dp_date": "2025-05-03T00:00:00", "eta_fd_date": "2025-05-20T00:00:00", "revised_eta_date": "2025-05-03T00:00:00", "predictive_eta_date": "2025-05-05T00:00:00", "atd_lp_date": "2025-02-07T00:00:00", "ata_flp_date": "2025-02-12T00:00:00", "atd_flp_date": "2025-02-27T00:00:00", "ata_dp_date": "2025-05-04T00:00:00", "derived_ata_dp_date": "2025-05-04T00:00:00", "revised_eta_fd_date": "2025-05-23T00:00:00", "predictive_eta_fd_date": "2025-05-23T00:00:00", "cargo_receiveds_date": ["2025-02-04T00:00:00", "2025-02-04T00:00:00"], "detention_free_days": "4.0", "demurrage_free_days": "4.0", "hot_container_flag": false, "supplier_vendor_name": "PINNACLE SPORTING GOODS (MYANMAR)(0038566)", "manufacturer_name": "PINNACLE SPORTING GOODS (MYANMAR)(0038566)", "ship_to_party_name": "NAN", "booking_approval_status": "(MM2003117)", "service_contract_number": "ATL0055B24(MM2003117)", "carrier_vehicle_load_date": "2025-02-06T00:00:00", "carrier_vehicle_load_lcn": "YANGON(MMRGN)", "vehicle_departure_date": "2025-02-07T00:00:00", "vehicle_departure_lcn": "YANGON(MMRGN)", "vehicle_arrival_date": "2025-05-04T00:00:00", "vehicle_arrival_lcn": "VANCOUVER, BC(CAVAN)", "carrier_vehicle_unload_date": "2025-05-05T00:00:00", "carrier_vehicle_unload_lcn": "VANCOUVER, BC(CAVAN)", "out_gate_from_dp_date": "2025-05-06T00:00:00", "out_gate_from_dp_lcn": "VANCOUVER, BC(CAVAN)", "equipment_arrived_at_last_cy_date": "2025-05-12T00:00:00", "equipment_arrived_at_last_cy_lcn": "TORONTO, ON(CATOR)", "out_gate_at_last_cy_date": "NaT", "out_gate_at_last_cy_lcn": "NAN", "delivery_to_consignee_date": "2025-05-13T00:00:00", "delivery_to_consignee_lcn": "BELLEVILLE, ON(CABLV)", "empty_container_return_date": "2025-05-14T00:00:00", "empty_container_return_lcn": "TORONTO, ON(CATOR)", "co2_tank_on_wheel": "135.267", "co2_well_to_wheel": "148.369", "job_type": "OCB", "mcs_hbl": "NAN", "transport_mode": "SEA", "rail_load_dp_date": "2025-05-05T00:00:00", "rail_load_dp_lcn": "VANCOUVER, BC(CAVAN)", "rail_departure_dp_date": "2025-05-10T00:00:00", "rail_departure_dp_lcn": "WINNIPEG, MB(CAWNP)", "rail_arrival_destination_date": "2025-05-13T00:00:00", "rail_arrival_destination_lcn": "BRAMPTON, ON(CABRP)", "cargo_ready_date": ["2025-02-03T00:00:00", "2025-02-03T00:00:00"], "in-dc_date": "NaT", "cargo_weight_kg": "1266.5", "cargo_measure_cubic_meter": "25.2", "cargo_count": "300", "cargo_um": "CTN", "cargo_detail_count": "300", "detail_cargo_um": "PCS", "856_filing_status": "", "get_isf_submission_date": null, "seal_number": "SGAH04573", "in_gate_date": "2025-02-04T00:00:00", "in_gate_lcn": "YANGON(MMRGN)", "empty_container_dispatch_date": "2025-02-01T00:00:00", "empty_container_dispatch_lcn": "YANGON(MMRGN)", "consignee_name": "WILSON CANADA", "consignee_codes": ["0001615"], "optimal_ata_dp_date": "2025-05-04T00:00:00", "optimal_eta_fd_date": "2025-05-23T00:00:00", "delayed_dp": "delay", "dp_delayed_dur": 1, "delayed_fd": "early", "fd_delayed_dur": -10, "shipment_status": "EMPTY_CONTAINER_RETURNED", "critical_dates_summary": "Leg 1 (POR → Load Port): YANGON(MMRGN) → YANGON(MMRGN) | ETD 07-Feb-25, ATD 07-Feb-25 || Leg 2 (Load → TS): YANGON(MMRGN) → SINGAPORE(SGSIN) | ATA 12-Feb-25, ATD 27-Feb-25 || Leg 3 (Ocean to DP): SINGAPORE(SGSIN) → VANCOUVER, BC(CAVAN) | ATA_DP 04-May-25 || Leg 4 (DP → Last CY): VANCOUVER, BC(CAVAN) → TORONTO, ON(CATOR) | OUT_GATE_DP 06-May-25, ARR_LAST_CY 12-May-25 || Leg 5 (Last CY → Final): TORONTO, ON(CATOR) → BELLEVILLE, ON(CABLV) | DELIVERY 13-May-25, EMPTY_RET 14-May-25", "delay_reason_summary": "Ocean / discharge-port leg is delayed versus ETA at DP by ~1 day(s).", "workflow_gap_flags": "none_detected", "milestones": "Overall shipment status: EMPTY CONTAINER RETURNED || Leg 1 (POR → Load Port) [COMPLETED]: YANGON(MMRGN) → YANGON(MMRGN); departed YANGON(MMRGN) on 2025-02-07. || Leg 2 (Load Port → TS) [COMPLETED]: YANGON(MMRGN) → SINGAPORE(SGSIN); arrived TS SINGAPORE(SGSIN) on 2025-02-12; departed TS on 2025-02-27 || Leg 3 (TS/Load → DP) [COMPLETED]: SINGAPORE(SGSIN) → VANCOUVER, BC(CAVAN); arrived VANCOUVER, BC(CAVAN) on 2025-05-04 (delayed by ~1 day(s) vs ETA DP.) || Leg 4 (DP → Last CY) [COMPLETED]: VANCOUVER, BC(CAVAN) → TORONTO, ON(CATOR); departed DP area (VANCOUVER, BC(CAVAN)) on 2025-05-06, arrived TORONTO, ON(CATOR) on 2025-05-12. Rail events: rail load VANCOUVER, BC(CAVAN) on 2025-05-05; rail depart WINNIPEG, MB(CAWNP) on 2025-05-10; rail arrive BRAMPTON, ON(CABRP) on 2025-05-13 || Leg 5 (Last CY → Final) [COMPLETED]: TORONTO, ON(CATOR) → BELLEVILLE, ON(CABLV); delivered at BELLEVILLE, ON(CABLV) on 2025-05-13; empty container returned at TORONTO, ON(CATOR) on 2025-05-14 (early by ~10 day(s) vs ETA FD.)", "vessel_summary": "First vessel: CAPE FELTON | Final vessel: YM TRANQUILITY", "carrier_summary": "Operated by OCEAN NETWORK EXPRESS PTE. LTD", "port_route_summary": "Origin/Load: YANGON(MMRGN) → Transshipment: SINGAPORE(SGSIN) → Discharge: VANCOUVER, BC(CAVAN) → Delivery at: BELLEVILLE, ON(CABLV)", "source_group": "2025-02", "source_month_tag": "feb_25"}, "consignee_code": "['0001615']"}
