{"document_id": "320001079445", "content": "Container: HMMU9056839 (C5) | Consignee: ARC'TERYX EQUIPMENT HQ | Seal Number: HMM210988389 | Origin/Load: CHATTOGRAM(BDCGP) | Discharge: VANCOUVER, BC(CAVAN) → Last CY location: VANCOUVER, BC(CAVAN) | Final Destination: VANCOUVER, BC(CAVAN) | Destination service: CFS | Current shipment status: EMPTY CONTAINER RETURNED\n\nKey dates: ETD LP: 19-Jan-25 | ETA DP: 27-Apr-25 | ATA DP (optimal): 27-Apr-25 | ETA FD (optimal): 10-May-25 Delay snapshot: DP delay: on_time, Δ≈0 day(s) | FD delay: early, Δ≈-8 day(s)\n\nRoute summary: Origin/Load: CHATTOGRAM(BDCGP) → Transshipment: SINGAPORE(SGSIN) → Discharge: VANCOUVER, BC(CAVAN) Last CY location: VANCOUVER, BC(CAVAN) Vessel summary: First vessel: SINAR SABA | Final vessel: YM TRIUMPH Carrier summary: Operated by KINTETSU WORLD EXPRESS(HK)LIMITED | True operating carrier: HYUNDAI MERCHANT MARINE (HK) LTD\n\nMilestones: Overall shipment status: EMPTY CONTAINER RETURNED || Leg 1 (POR → Load Port) [OVERDUE]: CHATTOGRAM(BDCGP) → CHATTOGRAM(BDCGP); ETD 2025-01-19 passed; actual departure not recorded. || Leg 2 (Load Port → TS) [COMPLETED]: CHATTOGRAM(BDCGP) → SINGAPORE(SGSIN); departed TS on 2025-02-19 || Leg 3 (TS/Load → DP) [COMPLETED]: SINGAPORE(SGSIN) → VANCOUVER, BC(CAVAN); arrived VANCOUVER, BC(CAVAN) on 2025-04-27 (on time vs ETA DP.) || Leg 4 (DP → Last CY) [COMPLETED]: VANCOUVER, BC(CAVAN) → VANCOUVER, BC(CAVAN); departed DP area (VANCOUVER, BC(CAVAN)) on 2025-04-30, arrived VANCOUVER, BC(CAVAN) on 2025-04-28. || Leg 5 (Last CY → Final) [COMPLETED]: VANCOUVER, BC(CAVAN) → VANCOUVER, BC(CAVAN); departed last CY (VANCOUVER, BC(CAVAN)) on 2025-04-30; empty container returned at VANCOUVER, BC(CAVAN) on 2025-05-02 (early by ~8 day(s) vs ETA FD.) Critical dates: Leg 1 (POR → Load Port): CHATTOGRAM(BDCGP) → CHATTOGRAM(BDCGP) | ETD 19-Jan-25 || Leg 2 (Load → TS): CHATTOGRAM(BDCGP) → SINGAPORE(SGSIN) | ATD 19-Feb-25 || Leg 3 (Ocean to DP): SINGAPORE(SGSIN) → VANCOUVER, BC(CAVAN) | ATA_DP 27-Apr-25 || Leg 4 (DP → Last CY): VANCOUVER, BC(CAVAN) → VANCOUVER, BC(CAVAN) | OUT_GATE_DP 30-Apr-25, ARR_LAST_CY 28-Apr-25 || Leg 5 (Last CY → Final): VANCOUVER, BC(CAVAN) → VANCOUVER, BC(CAVAN) | EMPTY_RET 02-May-25 Delay analysis: Shipment is on time against configured DP / final destination ETAs. Workflow gaps: missing_delivery_event_with_empty_return\n\nOperational events: In-DC: 03-Apr-25 | Cargo ready: 15-Jan-25, 15-Jan-25 | Cargo received: 15-Jan-25, 15-Jan-25 | Carrier vehicle unload: 28-Apr-25 @ VANCOUVER, BC(CAVAN) | Vehicle arrival: 27-Apr-25 @ VANCOUVER, BC(CAVAN) | Out-gate from DP: 30-Apr-25 @ VANCOUVER, BC(CAVAN) | Equipment arrived at last CY: 28-Apr-25 @ VANCOUVER, BC(CAVAN) | Out-gate at last CY: 30-Apr-25 @ VANCOUVER, BC(CAVAN)\n\nCargo metrics: weight 659 kg volume 5.64 m3 Cargo count: 93 PCS Detail cargo: 1777 PCS CO2: tank-to-wheel 37.809 | well-to-wheel 41.577\n\nFree days: Demurrage free days: 4 | Detention free days: 4\n\nReferences: PO Numbers: 6300116993,6300116998,6300116999,6300117000,6300117002,6300117003,6300121168,6300139937 | Booking Numbers: BD2033853 | FCR Numbers: BD2033853 | Ocean BL Numbers: 640140011690 | Job No: BD2ARC2562 | Service Contract: (BD2033853)\n\nParties & service: Consignee: ARC'TERYX EQUIPMENT HQ | Ship-to party: ARCTERYX EQUIPMENT:A DIVISION OF AM(0042283) | Supplier/Vendor: YOUNGONE (CEPZ) LTD(0019875) | Manufacturer: YOUNGONE (CEPZ) LTD(0019875) | Job type: OCB | Transport mode: SEA | Hot container flag: False | Booking approval status: (BD2033853)", "metadata": {"job_no": "BD2ARC2562", "container_number": "HMMU9056839", "container_type": "C5", "destination_service": "CFS", "po_numbers": "6300116993,6300116998,6300116999,6300117000,6300117002,6300117003,6300121168,6300139937", "booking_numbers": "BD2033853", "fcr_numbers": "BD2033853", "obl_nos": "640140011690", "load_port": "CHATTOGRAM(BDCGP)", "final_load_port": "SINGAPORE(SGSIN)", "discharge_port": "VANCOUVER, BC(CAVAN)", "last_cy_location": "VANCOUVER, BC(CAVAN)", "place_of_receipt": "CHATTOGRAM(BDCGP)", "place_of_delivery": "VANCOUVER, BC(CAVAN)", "final_destination": "VANCOUVER, BC(CAVAN)", "first_vessel_name": "SINAR SABA", "final_carrier_name": "KINTETSU WORLD EXPRESS(HK)LIMITED", "final_vessel_name": "YM TRIUMPH", "true_carrier_scac_name": "HYUNDAI MERCHANT MARINE (HK) LTD", "etd_lp_date": "2025-01-19T00:00:00", "etd_flp_date": "2025-02-19T00:00:00", "eta_dp_date": "2025-04-27T00:00:00", "eta_fd_date": "2025-05-07T00:00:00", "revised_eta_date": "2025-04-27T00:00:00", "predictive_eta_date": "2025-04-27T00:00:00", "atd_lp_date": "NaT", "ata_flp_date": "NaT", "atd_flp_date": "2025-02-19T00:00:00", "ata_dp_date": "2025-04-27T00:00:00", "derived_ata_dp_date": "2025-04-27T00:00:00", "revised_eta_fd_date": "2025-05-10T00:00:00", "predictive_eta_fd_date": "2025-05-10T00:00:00", "cargo_receiveds_date": ["2025-01-15T00:00:00", "2025-01-15T00:00:00"], "detention_free_days": "4", "demurrage_free_days": "4", "hot_container_flag": false, "supplier_vendor_name": "YOUNGONE (CEPZ) LTD(0019875)", "manufacturer_name": "YOUNGONE (CEPZ) LTD(0019875)", "ship_to_party_name": "ARCTERYX EQUIPMENT:A DIVISION OF AM(0042283)", "booking_approval_status": "(BD2033853)", "service_contract_number": "(BD2033853)", "carrier_vehicle_load_date": "NaT", "carrier_vehicle_load_lcn": "", "vehicle_departure_date": "NaT", "vehicle_departure_lcn": "", "vehicle_arrival_date": "2025-04-27T00:00:00", "vehicle_arrival_lcn": "VANCOUVER, BC(CAVAN)", "carrier_vehicle_unload_date": "2025-04-28T00:00:00", "carrier_vehicle_unload_lcn": "VANCOUVER, BC(CAVAN)", "out_gate_from_dp_date": "2025-04-30T00:00:00", "out_gate_from_dp_lcn": "VANCOUVER, BC(CAVAN)", "equipment_arrived_at_last_cy_date": "2025-04-28T00:00:00", "equipment_arrived_at_last_cy_lcn": "VANCOUVER, BC(CAVAN)", "out_gate_at_last_cy_date": "2025-04-30T00:00:00", "out_gate_at_last_cy_lcn": "VANCOUVER, BC(CAVAN)", "delivery_to_consignee_date": "NaT", "delivery_to_consignee_lcn": "", "empty_container_return_date": "2025-05-02T00:00:00", "empty_container_return_lcn": "VANCOUVER, BC(CAVAN)", "co2_tank_on_wheel": "37.809", "co2_well_to_wheel": "41.577", "job_type": "OCB", "mcs_hbl": "", "transport_mode": "SEA", "rail_load_dp_date": "NaT", "rail_load_dp_lcn": "", "rail_departure_dp_date": "NaT", "rail_departure_dp_lcn": "", "rail_arrival_destination_date": "NaT", "rail_arrival_destination_lcn": "", "cargo_ready_date": ["2025-01-15T00:00:00", "2025-01-15T00:00:00"], "in-dc_date": "2025-04-03T00:00:00", "cargo_weight_kg": "659", "cargo_measure_cubic_meter": "5.64", "cargo_count": "93", "cargo_um": "PCS", "cargo_detail_count": "1777", "detail_cargo_um": "PCS", "856_filing_status": "", "get_isf_submission_date": null, "seal_number": "HMM210988389", "in_gate_date": "NaT", "in_gate_lcn": "", "empty_container_dispatch_date": "NaT", "empty_container_dispatch_lcn": "", "consignee_name": "ARC'TERYX EQUIPMENT HQ", "consignee_codes": ["0028664"], "optimal_ata_dp_date": "2025-04-27T00:00:00", "optimal_eta_fd_date": "2025-05-10T00:00:00", "delayed_dp": "on_time", "dp_delayed_dur": 0, "delayed_fd": "early", "fd_delayed_dur": -8, "shipment_status": "EMPTY_CONTAINER_RETURNED", "critical_dates_summary": "Leg 1 (POR → Load Port): CHATTOGRAM(BDCGP) → CHATTOGRAM(BDCGP) | ETD 19-Jan-25 || Leg 2 (Load → TS): CHATTOGRAM(BDCGP) → SINGAPORE(SGSIN) | ATD 19-Feb-25 || Leg 3 (Ocean to DP): SINGAPORE(SGSIN) → VANCOUVER, BC(CAVAN) | ATA_DP 27-Apr-25 || Leg 4 (DP → Last CY): VANCOUVER, BC(CAVAN) → VANCOUVER, BC(CAVAN) | OUT_GATE_DP 30-Apr-25, ARR_LAST_CY 28-Apr-25 || Leg 5 (Last CY → Final): VANCOUVER, BC(CAVAN) → VANCOUVER, BC(CAVAN) | EMPTY_RET 02-May-25", "delay_reason_summary": "Shipment is on time against configured DP / final destination ETAs.", "workflow_gap_flags": "missing_delivery_event_with_empty_return", "milestones": "Overall shipment status: EMPTY CONTAINER RETURNED || Leg 1 (POR → Load Port) [OVERDUE]: CHATTOGRAM(BDCGP) → CHATTOGRAM(BDCGP); ETD 2025-01-19 passed; actual departure not recorded. || Leg 2 (Load Port → TS) [COMPLETED]: CHATTOGRAM(BDCGP) → SINGAPORE(SGSIN); departed TS on 2025-02-19 || Leg 3 (TS/Load → DP) [COMPLETED]: SINGAPORE(SGSIN) → VANCOUVER, BC(CAVAN); arrived VANCOUVER, BC(CAVAN) on 2025-04-27 (on time vs ETA DP.) || Leg 4 (DP → Last CY) [COMPLETED]: VANCOUVER, BC(CAVAN) → VANCOUVER, BC(CAVAN); departed DP area (VANCOUVER, BC(CAVAN)) on 2025-04-30, arrived VANCOUVER, BC(CAVAN) on 2025-04-28. || Leg 5 (Last CY → Final) [COMPLETED]: VANCOUVER, BC(CAVAN) → VANCOUVER, BC(CAVAN); departed last CY (VANCOUVER, BC(CAVAN)) on 2025-04-30; empty container returned at VANCOUVER, BC(CAVAN) on 2025-05-02 (early by ~8 day(s) vs ETA FD.)", "vessel_summary": "First vessel: SINAR SABA | Final vessel: YM TRIUMPH", "carrier_summary": "Operated by KINTETSU WORLD EXPRESS(HK)LIMITED | True operating carrier: HYUNDAI MERCHANT MARINE (HK) LTD", "port_route_summary": "Origin/Load: CHATTOGRAM(BDCGP) → Transshipment: SINGAPORE(SGSIN) → Discharge: VANCOUVER, BC(CAVAN)", "source_group": "2025-01", "source_month_tag": "jan_25"}, "consignee_code": "['0028664']"}
